data_detector-0.0.1.dist-info/licenses/LICENSE
datadetector/__init__.py
datadetector/cli.py
datadetector/engine.py
datadetector/models.py
datadetector/py.typed
datadetector/registry.py
datadetector/restore_tokens.py
datadetector/server.py
datadetector/verification.py
datadetector/yaml_utils.py
data_detector-0.0.1.dist-info/METADATA
data_detector-0.0.1.dist-info/WHEEL
data_detector-0.0.1.dist-info/entry_points.txt
data_detector-0.0.1.dist-info/top_level.txt
data_detector-0.0.1.dist-info/RECORD
