Metadata-Version: 2.4
Name: data-detector
Version: 0.0.1
Summary: A general-purpose engine that detects and masks personal information by country and information type
Author-email: zafrem <zafrem@gmail.com>
License: MIT
Project-URL: Homepage, https://github.com/zafrem/data-detector
Project-URL: Repository, https://github.com/zafrem/data-detector
Project-URL: Issues, https://github.com/zafrem/data-detector/issues
Keywords: pii,detection,redaction,regex,privacy,gdpr
Classifier: Development Status :: 3 - Alpha
Classifier: Intended Audience :: Developers
Classifier: License :: OSI Approved :: MIT License
Classifier: Programming Language :: Python :: 3
Classifier: Programming Language :: Python :: 3.8
Classifier: Programming Language :: Python :: 3.9
Classifier: Programming Language :: Python :: 3.10
Classifier: Programming Language :: Python :: 3.11
Classifier: Programming Language :: Python :: 3.12
Requires-Python: >=3.8
License-File: LICENSE
Requires-Dist: pyyaml>=6.0
Requires-Dist: jsonschema>=4.17.0
Requires-Dist: click>=8.1.0
Requires-Dist: fastapi>=0.104.0
Requires-Dist: uvicorn[standard]>=0.24.0
Requires-Dist: grpcio>=1.59.0
Requires-Dist: grpcio-tools>=1.59.0
Requires-Dist: prometheus-client>=0.19.0
Requires-Dist: pydantic>=2.0.0
Requires-Dist: python-multipart>=0.0.6
Provides-Extra: dev
Requires-Dist: pytest>=7.4.0; extra == "dev"
Requires-Dist: pytest-cov>=4.1.0; extra == "dev"
Requires-Dist: pytest-asyncio>=0.21.0; extra == "dev"
Requires-Dist: black>=23.0.0; extra == "dev"
Requires-Dist: ruff>=0.1.0; extra == "dev"
Requires-Dist: mypy>=1.5.0; extra == "dev"
Requires-Dist: types-pyyaml; extra == "dev"
Requires-Dist: types-jsonschema; extra == "dev"
Provides-Extra: test
Requires-Dist: pytest>=7.4.0; extra == "test"
Requires-Dist: pytest-cov>=4.1.0; extra == "test"
Requires-Dist: pytest-asyncio>=0.21.0; extra == "test"
Requires-Dist: httpx>=0.25.0; extra == "test"
Dynamic: license-file
